{"nodes": [{"id": "creatingprd_overview", "label": "creating-prd overview", "file_type": "document", "source_file": "skills/creating-prd/SKILL.md", "source_location": "Header / intro", "source_url": null, "captured_at": null, "author": null, "contributor": null}, {"id": "creatingprd_create_mode", "label": "Create Mode checklist and process", "file_type": "document", "source_file": "skills/creating-prd/SKILL.md", "source_location": "Checklist (Create Mode)", "source_url": null, "captured_at": null, "author": null, "contributor": null}, {"id": "creatingprd_update_mode", "label": "Update Mode overview", "file_type": "document", "source_file": "skills/creating-prd/SKILL.md", "source_location": "Update Mode", "source_url": null, "captured_at": null, "author": null, "contributor": null}, {"id": "creatingprd_discovery_questions", "label": "Discovery Questions (7 questions)", "file_type": "document", "source_file": "skills/creating-prd/SKILL.md", "source_location": "Discovery Questions", "source_url": null, "captured_at": null, "author": null, "contributor": null}, {"id": "creatingprd_prd_structure", "label": "PRD Structure (15 sections, two parts)", "file_type": "document", "source_file": "skills/creating-prd/SKILL.md", "source_location": "PRD Structure", "source_url": null, "captured_at": null, "author": null, "contributor": null}, {"id": "creatingprd_id_conventions", "label": "ID Conventions (US-###, AC-###.#, Q-###)", "file_type": "document", "source_file": "skills/creating-prd/SKILL.md", "source_location": "ID Conventions", "source_url": null, "captured_at": null, "author": null, "contributor": null}], "edges": [{"source": "creatingprd_overview", "target": "creatingprd_create_mode", "relation": "references", "confidence": "EXTRACTED", "confidence_score": 1.0, "source_file": "skills/creating-prd/SKILL.md", "source_location": "Checklist (Create Mode)", "weight": 1.0}, {"source": "creatingprd_overview", "target": "creatingprd_update_mode", "relation": "references", "confidence": "EXTRACTED", "confidence_score": 1.0, "source_file": "skills/creating-prd/SKILL.md", "source_location": "Update Mode", "weight": 1.0}, {"source": "creatingprd_create_mode", "target": "creatingprd_discovery_questions", "relation": "references", "confidence": "EXTRACTED", "confidence_score": 1.0, "source_file": "skills/creating-prd/SKILL.md", "source_location": "Step 5: Discovery questions", "weight": 1.0}, {"source": "creatingprd_create_mode", "target": "creatingprd_prd_structure", "relation": "references", "confidence": "EXTRACTED", "confidence_score": 1.0, "source_file": "skills/creating-prd/SKILL.md", "source_location": "Step 6: Draft and present", "weight": 1.0}, {"source": "creatingprd_prd_structure", "target": "creatingprd_id_conventions", "relation": "references", "confidence": "EXTRACTED", "confidence_score": 1.0, "source_file": "skills/creating-prd/SKILL.md", "source_location": "ID Conventions", "weight": 1.0}, {"source": "creatingprd_overview", "target": "milestoneplanning_overview", "relation": "references", "confidence": "EXTRACTED", "confidence_score": 1.0, "source_file": "skills/creating-prd/SKILL.md", "source_location": "Step 8: Handoff", "weight": 1.0}, {"source": "creatingprd_discovery_questions", "target": "external_closedloop_prd_creator", "relation": "cites", "confidence": "EXTRACTED", "confidence_score": 1.0, "source_file": "skills/creating-prd/SKILL.md", "source_location": "intro paragraph", "weight": 1.0}, {"source": "creatingprd_id_conventions", "target": "external_closedloop_prd_creator", "relation": "cites", "confidence": "EXTRACTED", "confidence_score": 1.0, "source_file": "skills/creating-prd/SKILL.md", "source_location": "intro paragraph", "weight": 1.0}], "hyperedges": []}